face_recognition/__init__.py
face_recognition/api.py
face_recognition/face_detection_cli.py
face_recognition/face_recognition_cli.py
persona_cipher/__init__.py
persona_cipher/create_dataset.py
persona_cipher/fetch_info.py
persona_cipher/mp4_downloader.py
persona_cipher/persona_cipher.py
persona_cipher/datasets/__init__.py
persona_cipher/datasets/usernames.txt
personacipher-5.1.1.dist-info/licenses/LICENSE
personacipher-5.1.1.dist-info/METADATA
personacipher-5.1.1.dist-info/WHEEL
personacipher-5.1.1.dist-info/entry_points.txt
personacipher-5.1.1.dist-info/top_level.txt
personacipher-5.1.1.dist-info/RECORD
