Metadata-Version: 2.4
Name: PersonaCipher
Version: 5.1.1
Summary: Your face recognizer in images & videos.
Home-page: https://github.com/cyb2rS2c/PersonaCipher
Author: cyb2rS2c
License: MIT
Classifier: Programming Language :: Python :: 3
Classifier: License :: OSI Approved :: MIT License
Classifier: Operating System :: OS Independent
Requires-Python: >=3.7
License-File: LICENSE
Requires-Dist: opencv-python
Requires-Dist: pillow
Requires-Dist: numpy
Requires-Dist: dlib
Requires-Dist: requests
Requires-Dist: beautifulsoup4
Requires-Dist: pyfiglet
Requires-Dist: colorama
Requires-Dist: yt_dlp
Requires-Dist: face-recognition-models
Requires-Dist: face-recognition
Requires-Dist: setuptools<81.0
Dynamic: author
Dynamic: classifier
Dynamic: description
Dynamic: description-content-type
Dynamic: home-page
Dynamic: license
Dynamic: license-file
Dynamic: requires-dist
Dynamic: requires-python
Dynamic: summary
